docker_helper.py
ecs_helper.py
slack_api.py
commons/__init__.py
commons/config.py
commons/constant.py
print_sid-0.1.data/scripts/dokr
utils/__init__.py
utils/helper.py
utils/http_client.py
utils/logger.py
print_sid-0.1.dist-info/LICENSE
print_sid-0.1.dist-info/METADATA
print_sid-0.1.dist-info/WHEEL
print_sid-0.1.dist-info/top_level.txt
print_sid-0.1.dist-info/RECORD
